edk2_pytool_extensions-0.30.5.dist-info/licenses/LICENSE
edk2toolext/__init__.py
edk2toolext/base_abstract_invocable.py
edk2toolext/codeql.py
edk2toolext/edk2_invocable.py
edk2toolext/edk2_logging.py
edk2toolext/edk2_report.py
edk2toolext/image_validation.py
edk2toolext/nuget_publishing.py
edk2toolext/omnicache.py
edk2toolext/bin/NuGet.exe
edk2toolext/bin/__init__.py
edk2toolext/bin/nuget.py
edk2toolext/bin/readme.md
edk2toolext/capsule/__init__.py
edk2toolext/capsule/capsule_helper.py
edk2toolext/capsule/capsule_tool.py
edk2toolext/capsule/pyopenssl_signer.py
edk2toolext/capsule/signing_helper.py
edk2toolext/capsule/signtool_signer.py
edk2toolext/environment/__init__.py
edk2toolext/environment/conf_mgmt.py
edk2toolext/environment/environment_descriptor_files.py
edk2toolext/environment/external_dependency.py
edk2toolext/environment/multiple_workspace.py
edk2toolext/environment/plugin_manager.py
edk2toolext/environment/repo_resolver.py
edk2toolext/environment/rust.py
edk2toolext/environment/self_describing_environment.py
edk2toolext/environment/shell_environment.py
edk2toolext/environment/uefi_build.py
edk2toolext/environment/var_dict.py
edk2toolext/environment/version_aggregator.py
edk2toolext/environment/extdeptypes/__init__.py
edk2toolext/environment/extdeptypes/az_cli_universal_dependency.py
edk2toolext/environment/extdeptypes/git_dependency.py
edk2toolext/environment/extdeptypes/nuget_dependency.py
edk2toolext/environment/extdeptypes/web_dependency.py
edk2toolext/environment/plugintypes/__init__.py
edk2toolext/environment/plugintypes/ci_build_plugin.py
edk2toolext/environment/plugintypes/dsc_processor_plugin.py
edk2toolext/environment/plugintypes/uefi_build_plugin.py
edk2toolext/environment/plugintypes/uefi_helper_plugin.py
edk2toolext/environment/reporttypes/__init__.py
edk2toolext/environment/reporttypes/base_report.py
edk2toolext/environment/reporttypes/component_report.py
edk2toolext/environment/reporttypes/coverage_report.py
edk2toolext/environment/reporttypes/usage_report.py
edk2_pytool_extensions-0.30.5.dist-info/METADATA
edk2_pytool_extensions-0.30.5.dist-info/WHEEL
edk2_pytool_extensions-0.30.5.dist-info/entry_points.txt
edk2_pytool_extensions-0.30.5.dist-info/top_level.txt
edk2_pytool_extensions-0.30.5.dist-info/RECORD
