Metadata-Version: 2.4
Name: edk2-pytool-extensions
Version: 0.30.5
Summary: Python tools supporting UEFI EDK2 firmware development
Maintainer-email: EDK2 Pytool Maintainers <edk2-pytools@microsoft.com>
Project-URL: homepage, https://github.com/tianocore/edk2-pytool-extensions
Project-URL: documentation, https://www.tianocore.org/edk2-pytool-extensions/
Project-URL: issues, https://github.com/tianocore/edk2-pytool-extensions/issues
Classifier: Programming Language :: Python :: 3
Classifier: Operating System :: OS Independent
Classifier: Development Status :: 4 - Beta
Classifier: Intended Audience :: Developers
Classifier: Programming Language :: Python :: 3.10
Classifier: Programming Language :: Python :: 3.11
Classifier: Programming Language :: Python :: 3.12
Classifier: Programming Language :: Python :: 3.13
Classifier: Programming Language :: Python :: 3.14
Requires-Python: >=3.10
License-File: LICENSE
Requires-Dist: edk2-pytool-library>=0.23.10
Requires-Dist: pyyaml>=6.0.0
Requires-Dist: pefile>=2023.2.7
Requires-Dist: semantic_version>=2.10.0
Requires-Dist: GitPython>=3.1.30
Requires-Dist: openpyxl>=3.1.2
Requires-Dist: XlsxWriter>=3.0.9
Requires-Dist: pywin32>=305; sys_platform == "win32"
Requires-Dist: setuptools>=78.1.1
Provides-Extra: dev
Requires-Dist: edk2-pytool-extensions[openssl]; extra == "dev"
Requires-Dist: ruff==0.14.1; extra == "dev"
Requires-Dist: pytest==8.4.2; extra == "dev"
Requires-Dist: coverage==7.11.0; extra == "dev"
Requires-Dist: robotframework==7.3.2; extra == "dev"
Requires-Dist: regex==2025.9.18; extra == "dev"
Requires-Dist: pre-commit==4.1.0; extra == "dev"
Provides-Extra: publish
Requires-Dist: setuptools==80.9.0; extra == "publish"
Requires-Dist: build==1.3.0; extra == "publish"
Requires-Dist: twine==6.2.0; extra == "publish"
Provides-Extra: docs
Requires-Dist: black==25.9.0; extra == "docs"
Requires-Dist: mkdocs==1.6.1; extra == "docs"
Requires-Dist: mkdocs-material==9.6.22; extra == "docs"
Requires-Dist: mkdocstrings[python]==0.30.1; extra == "docs"
Requires-Dist: mkdocstrings-python==1.18.2; extra == "docs"
Requires-Dist: markdown-include==0.8.1; extra == "docs"
Requires-Dist: mkdocs-gen-files==0.5.0; extra == "docs"
Requires-Dist: mkdocs-exclude==1.0.2; extra == "docs"
Requires-Dist: mkdocs-awesome-pages-plugin==2.10.1; extra == "docs"
Provides-Extra: openssl
Requires-Dist: pyopenssl; extra == "openssl"
Requires-Dist: cryptography>=39.0.1; extra == "openssl"
Provides-Extra: perf
Requires-Dist: wmi>=1.5.0; sys_platform == "win32" and extra == "perf"
Dynamic: license-file
